setup.cfg
setup.py
pycsco/__init__.py
pycsco.egg-info/PKG-INFO
pycsco.egg-info/SOURCES.txt
pycsco.egg-info/dependency_links.txt
pycsco.egg-info/requires.txt
pycsco.egg-info/top_level.txt
pycsco/nxos/__init__.py
pycsco/nxos/device.py
pycsco/nxos/nxapi.py
pycsco/nxos/utils/__init__.py
pycsco/nxos/utils/legacy.py
pycsco/nxos/utils/nxapi_lib.py
pycsco/nxos/utils/snmp.py