Metadata-Version: 1.1
Name: pycsco
Version: 0.2.2
Summary: Python modules to simplify working with Cisco NX-OS devices 
Home-page: https://github.com/jedelman8/pycsco
Author: Jason Edelman
Author-email: jedelman8@gmail.com
License: UNKNOWN
Download-URL: https://github.com/jedelman8/pycsco/tarball/0.2.2
Platform: UNKNOWN
